LICENSE
MANIFEST.in
README.rst
setup.py
HiCTornadIO2.egg-info/PKG-INFO
HiCTornadIO2.egg-info/SOURCES.txt
HiCTornadIO2.egg-info/dependency_links.txt
HiCTornadIO2.egg-info/pbr.json
HiCTornadIO2.egg-info/requires.txt
HiCTornadIO2.egg-info/top_level.txt
tornadio2/__init__.py
tornadio2/conn.py
tornadio2/flashserver.py
tornadio2/gen.py
tornadio2/periodic.py
tornadio2/persistent.py
tornadio2/polling.py
tornadio2/preflight.py
tornadio2/proto.py
tornadio2/router.py
tornadio2/server.py
tornadio2/session.py
tornadio2/sessioncontainer.py
tornadio2/stats.py