Metadata-Version: 1.1
Name: HiCTornadIO2
Version: 0.1.2
Summary: Fork of TornadIO2 0.0.4 (by Serge S. Koval). Socket.io 0.7+ server implementation on top of Tornado framework
Home-page: http://github.com/kulapard/tornadio2/
Author: Serge S. Koval, Taras Drapalyuk
Author-email: serge.koval@gmail.com, taras@drapalyuk.com
License: Copyright (c) 2011, Serge. S. Koval. <http://in-square.net/>
